EasyGraphLib/__init__.py
EasyGraphLib/graph.py
EasyGraphLib-0.3.5.dist-info/LICENCE.txt
EasyGraphLib-0.3.5.dist-info/METADATA
EasyGraphLib-0.3.5.dist-info/WHEEL
EasyGraphLib-0.3.5.dist-info/top_level.txt
EasyGraphLib-0.3.5.dist-info/RECORD
