Metadata-Version: 2.1
Name: EasyGraphLib
Version: 0.3.5
Summary: Python library for creating graphs, trees, and gemini structures.
Home-page: https://gitlab.com/AdamFull/easygraphlib
Author: Ilya Baranov
Author-email: logotipick@gmail.com
License: MIT License
Download-URL: https://gitlab.com/AdamFull/easygraphlib/blob/master/dist/EasyGraphLib-0.3.0-py3-none-any.whl
Keywords: Graph,Modeling,Structures
Platform: UNKNOWN
Classifier: Programming Language :: Python :: 3
Classifier: License :: OSI Approved :: MIT License
Classifier: Operating System :: OS Independent
